README
gherkin.py
setup.py
gherkin.egg-info/PKG-INFO
gherkin.egg-info/SOURCES.txt
gherkin.egg-info/dependency_links.txt
gherkin.egg-info/top_level.txt
